jencrypt/__init__.py
jencrypt/bootstrap.py
jencrypt-2.0.16.dist-info/entry_points.txt
jencrypt-2.0.16.dist-info/LICENSE
jencrypt-2.0.16.dist-info/WHEEL
jencrypt-2.0.16.dist-info/METADATA
jencrypt-2.0.16.dist-info/RECORD
