Metadata-Version: 2.1
Name: jencrypt
Version: 2.0.16
Summary: app
Home-page: https://github.com/JamesZBL/jencrypt
License: UNKNOWN
Author: JamesZBL@github.com
Author-email: zhengbaole@gmail.com
Classifier: License :: OSI Approved :: Apache Software License
Requires-Dist: watchdog
